scalebench/__init__.py
scalebench/benchmark_controller.py
scalebench/benchmark_core.py
scalebench/cli.py
scalebench/dataset_manager.py
scalebench/load_optimizer.py
scalebench/utils/__init__.py
scalebench/utils/metrics_processor.py
scalebench/utils/visualization.py
scalebench-0.1.4.dist-info/METADATA
scalebench-0.1.4.dist-info/WHEEL
scalebench-0.1.4.dist-info/entry_points.txt
scalebench-0.1.4.dist-info/top_level.txt
scalebench-0.1.4.dist-info/RECORD
