Metadata-Version: 2.4
Name: scalebench
Version: 0.1.4
Summary: LLM Inference Benchmarking Tool
Home-page: https://github.com/Infobellit-Solutions-Pvt-Ltd/ScaleBench_AI
Author: Infobell AI Team
Author-email: sarthak@infobellit.com
Classifier: Programming Language :: Python :: 3
Classifier: License :: OSI Approved :: MIT License
Classifier: Operating System :: OS Independent
Requires-Python: >=3.10
Requires-Dist: click
Requires-Dist: pyyaml
Requires-Dist: tqdm
Requires-Dist: pandas
Requires-Dist: matplotlib
Requires-Dist: locust
Requires-Dist: transformers
Requires-Dist: datasets
Requires-Dist: tabulate
Requires-Dist: keyboard
Dynamic: author
Dynamic: author-email
Dynamic: classifier
Dynamic: description
Dynamic: description-content-type
Dynamic: home-page
Dynamic: requires-dist
Dynamic: requires-python
Dynamic: summary
